__init__.py
traffic_simulation.py
traffic_simulation_numba.py
ai_traffic_light_simulator-1.0.1.dist-info/METADATA
ai_traffic_light_simulator-1.0.1.dist-info/WHEEL
ai_traffic_light_simulator-1.0.1.dist-info/top_level.txt
ai_traffic_light_simulator-1.0.1.dist-info/RECORD
