Metadata-Version: 2.1
Name: ai-traffic-light-simulator
Version: 1.0.1
Summary: Traffic simulation for traffic light A.I. training
Project-URL: Homepage, https://github.com/bart1259/TrafficLightAI
Keywords: artifical intelligence,traffic,traffic simulator,simulation,cellular automata
Classifier: License :: OSI Approved :: MIT License
Classifier: Programming Language :: Python
Classifier: Programming Language :: Python :: 3
Requires-Python: >=3.8
Requires-Dist: matplotlib (>=3.4.0)
Requires-Dist: numpy (>=1.20.0)
Requires-Dist: numba (>=0.50.0)
Provides-Extra: dev
